DeviceManager.py
README.md
asyncio_dvrip.py
dvrip.py
setup.cfg
setup.py
python_dvr.egg-info/PKG-INFO
python_dvr.egg-info/SOURCES.txt
python_dvr.egg-info/dependency_links.txt
python_dvr.egg-info/top_level.txt