Metadata-Version: 2.1
Name: python-dvr
Version: 0.0.1
Summary: Python library for configuring a wide range of IP cameras which use the NETsurveillance ActiveX plugin XMeye SDK
Home-page: https://github.com/NeiroNx/python-dvr/
Author: NeiroN
License: MIT
Project-URL: Bug Reports, https://github.com/NeiroNx/python-dvr/issues
Project-URL: Source, https://github.com/NeiroNx/python-dvr
Platform: UNKNOWN
Classifier: Development Status :: 3 - Alpha
Classifier: Intended Audience :: Developers
Classifier: Topic :: Multimedia :: Video :: Capture
Classifier: License :: OSI Approved :: MIT License
Classifier: Programming Language :: Python :: 3
Classifier: Programming Language :: Python :: 3.6
Classifier: Programming Language :: Python :: 3.7
Classifier: Programming Language :: Python :: 3.8
Classifier: Programming Language :: Python :: 3.9
Classifier: Programming Language :: Python :: 3 :: Only
Requires-Python: >=3.6
